spreadsheet_wrangler/.editorconfig
spreadsheet_wrangler/.gitignore
spreadsheet_wrangler/.travis.yml
spreadsheet_wrangler/__init__.py
spreadsheet_wrangler/cli.py
spreadsheet_wrangler/spreadsheet_wrangler.py
spreadsheet_wrangler/.github/ISSUE_TEMPLATE.md
spreadsheet_wrangler-0.1.6.dist-info/LICENSE
spreadsheet_wrangler-0.1.6.dist-info/METADATA
spreadsheet_wrangler-0.1.6.dist-info/WHEEL
spreadsheet_wrangler-0.1.6.dist-info/entry_points.txt
spreadsheet_wrangler-0.1.6.dist-info/top_level.txt
spreadsheet_wrangler-0.1.6.dist-info/RECORD
