Metadata-Version: 2.1
Name: spreadsheet_wrangler
Version: 0.1.6
Summary: Place components in a kicad file programmatically.
Author-email: Simon Hobbs <simon.hobbs@electrooptical.net>
License: MIT License
Project-URL: github, https://github.com/snhobbs/spreadsheet-wrangler.git
Keywords: spreadsheet_wrangler,kicad,python,eda,electronics,pcb,manufacturing
Classifier: Development Status :: 2 - Pre-Alpha
Classifier: Intended Audience :: Developers
Classifier: Natural Language :: English
Classifier: Programming Language :: Python :: 3
Requires-Python: >=3.8
License-File: LICENSE
Requires-Dist: click >=7.0.0
Requires-Dist: pandas >=2.0.0
Requires-Dist: pyexcel-ods3 >=0.6.0
